chaoshen_mcp_demo/__init__.py
chaoshen_mcp_demo-0.1.0.dist-info/METADATA
chaoshen_mcp_demo-0.1.0.dist-info/WHEEL
chaoshen_mcp_demo-0.1.0.dist-info/entry_points.txt
chaoshen_mcp_demo-0.1.0.dist-info/RECORD
